python_open_router/__init__.py
python_open_router/exceptions.py
python_open_router/models.py
python_open_router/open_router.py
python_open_router/py.typed
python_open_router-0.3.3.dist-info/METADATA
python_open_router-0.3.3.dist-info/WHEEL
python_open_router-0.3.3.dist-info/licenses/LICENSE.md
python_open_router-0.3.3.dist-info/RECORD
